ChatSelfbot/__init__.py
ChatSelfbot/_selfbot.py
chatselfbot-1.3.0.dist-info/licenses/LICENSE
chatselfbot-1.3.0.dist-info/METADATA
chatselfbot-1.3.0.dist-info/WHEEL
chatselfbot-1.3.0.dist-info/top_level.txt
chatselfbot-1.3.0.dist-info/RECORD
