Metadata-Version: 2.4
Name: ChatSelfbot
Version: 1.3.0
Summary: A fast and light selfbot made by Bjarnos for Chat (a program by Jona Zwetsloot)!
Home-page: https://github.com/Bjarnos/SelfbotSource
Author: Bjarnos
Author-email: Bjarnos <contact@bjarnos.dev>
License: Copyright (c) 2025 Bjarnos
Project-URL: Homepage, https://github.com/Bjarnos/SelfbotSource
Project-URL: Issues, https://github.com/Bjarnos/SelfbotSource/issues
Classifier: Programming Language :: Python :: 3
Classifier: Operating System :: OS Independent
Requires-Python: >=3.8
License-File: LICENSE
Requires-Dist: beautifulsoup4
Requires-Dist: requests
Dynamic: author
Dynamic: home-page
Dynamic: license-file
Dynamic: requires-python
